yta_audio_transcription/__init__.py
yta_audio_transcription/objects.py
yta_audio_transcription/whisper.py
yta_audio_transcription-0.0.6.dist-info/licenses/LICENSE
yta_audio_transcription-0.0.6.dist-info/METADATA
yta_audio_transcription-0.0.6.dist-info/WHEEL
yta_audio_transcription-0.0.6.dist-info/RECORD
