Metadata-Version: 2.4
Name: yta-audio-transcription
Version: 0.0.6
Summary: Youtube Autonomous Audio Transcription Module.
License-File: LICENSE
Author: danialcala94
Author-email: danielalcalavalera@gmail.com
Requires-Python: ==3.9
Classifier: Programming Language :: Python :: 3
Classifier: Programming Language :: Python :: 3.9
Requires-Dist: numpy (>=0.0.1,<9.0.0)
Requires-Dist: whisper-timestamped (>=1.0.0,<9.0.0)
Requires-Dist: yta_constants (>=0.0.1,<1.0.0)
Requires-Dist: yta_file (>=0.0.1,<1.0.0)
Requires-Dist: yta_programming (>=0.0.1,<1.0.0)
Requires-Dist: yta_temp (>=0.0.1,<1.0.0)
Requires-Dist: yta_validation (>=0.0.1,<1.0.0)
